home_sensu_checks
